karrio/mappers/locate2u/__init__.py
karrio/mappers/locate2u/mapper.py
karrio/mappers/locate2u/proxy.py
karrio/mappers/locate2u/settings.py
karrio/plugins/locate2u/__init__.py
karrio/providers/locate2u/__init__.py
karrio/providers/locate2u/error.py
karrio/providers/locate2u/tracking.py
karrio/providers/locate2u/units.py
karrio/providers/locate2u/utils.py
karrio/providers/locate2u/shipment/__init__.py
karrio/providers/locate2u/shipment/cancel.py
karrio/providers/locate2u/shipment/create.py
karrio/schemas/locate2u/__init__.py
karrio/schemas/locate2u/shipping_request.py
karrio/schemas/locate2u/shipping_response.py
karrio/schemas/locate2u/tracking_response.py
karrio_locate2u-2026.1.4.dist-info/METADATA
karrio_locate2u-2026.1.4.dist-info/WHEEL
karrio_locate2u-2026.1.4.dist-info/entry_points.txt
karrio_locate2u-2026.1.4.dist-info/top_level.txt
karrio_locate2u-2026.1.4.dist-info/RECORD
